{
	"Version": 3,
	"Parameters": [
		{
			"Id": "ParamAngleX",
			"GroupId": "",
			"Name": "角度 X"
		},
		{
			"Id": "ParamAngleY",
			"GroupId": "",
			"Name": "角度 Y"
		},
		{
			"Id": "ParamAngleZ",
			"GroupId": "",
			"Name": "角度 Z"
		},
		{
			"Id": "ParamEyeLOpen",
			"GroupId": "",
			"Name": "左目　開閉"
		},
		{
			"Id": "ParamEyeLSmile",
			"GroupId": "",
			"Name": "左目　笑顔"
		},
		{
			"Id": "ParamEyeROpen",
			"GroupId": "",
			"Name": "右目　開閉"
		},
		{
			"Id": "ParamEyeRSmile",
			"GroupId": "",
			"Name": "右目　笑顔"
		},
		{
			"Id": "ParamEyeBallX",
			"GroupId": "",
			"Name": "目玉 X"
		},
		{
			"Id": "ParamEyeBallY",
			"GroupId": "",
			"Name": "目玉 Y"
		},
		{
			"Id": "ParamBrowLY",
			"GroupId": "",
			"Name": "左眉　上下"
		},
		{
			"Id": "ParamBrowRY",
			"GroupId": "",
			"Name": "右眉　上下"
		},
		{
			"Id": "ParamBrowLX",
			"GroupId": "",
			"Name": "左眉　左右"
		},
		{
			"Id": "ParamBrowRX",
			"GroupId": "",
			"Name": "右眉　左右"
		},
		{
			"Id": "ParamBrowLAngle",
			"GroupId": "",
			"Name": "左眉　角度"
		},
		{
			"Id": "ParamBrowRAngle",
			"GroupId": "",
			"Name": "右眉　角度"
		},
		{
			"Id": "ParamBrowLForm",
			"GroupId": "",
			"Name": "左眉　変形"
		},
		{
			"Id": "ParamBrowRForm",
			"GroupId": "",
			"Name": "右眉　変形"
		},
		{
			"Id": "ParamMouthForm",
			"GroupId": "",
			"Name": "口　変形"
		},
		{
			"Id": "ParamMouthOpenY",
			"GroupId": "",
			"Name": "口　開閉"
		},
		{
			"Id": "ParamCheek",
			"GroupId": "",
			"Name": "照れ"
		},
		{
			"Id": "ParamBodyAngleX",
			"GroupId": "",
			"Name": "体の回転　X"
		},
		{
			"Id": "ParamBodyAngleY",
			"GroupId": "",
			"Name": "体の回転　Y"
		},
		{
			"Id": "ParamBodyAngleZ",
			"GroupId": "",
			"Name": "体の回転　Z"
		},
		{
			"Id": "ParamBreath",
			"GroupId": "",
			"Name": "呼吸"
		},
		{
			"Id": "ParamHairFront",
			"GroupId": "",
			"Name": "髪揺れ　前"
		},
		{
			"Id": "ParamHairSide",
			"GroupId": "",
			"Name": "髪揺れ　横"
		},
		{
			"Id": "ParamHairBack",
			"GroupId": "",
			"Name": "髪揺れ　後"
		},
		{
			"Id": "ParamTwintail",
			"GroupId": "",
			"Name": "ツインテール揺れ"
		},
		{
			"Id": "ParamRibon",
			"GroupId": "",
			"Name": "リボン揺れ"
		},
		{
			"Id": "ParamSkart",
			"GroupId": "",
			"Name": "スカート揺れ"
		},
		{
			"Id": "ParamSerllar",
			"GroupId": "",
			"Name": "セーラー後ろ揺れ"
		},
		{
			"Id": "ParamDress",
			"GroupId": "",
			"Name": "装飾揺れ"
		},
		{
			"Id": "ParamRight_hilight",
			"GroupId": "",
			"Name": "右目ハイライト揺れ"
		},
		{
			"Id": "ParamLeftHilight",
			"GroupId": "",
			"Name": "左目ハイライト揺れ"
		},
		{
			"Id": "ParamSmallEye",
			"GroupId": "",
			"Name": "目　縮小"
		}
	],
	"ParameterGroups": [],
	"Parts": [
		{
			"Id": "Part",
			"Name": "頭部"
		},
		{
			"Id": "Part3",
			"Name": "ポニテ"
		},
		{
			"Id": "Part8",
			"Name": "身体"
		},
		{
			"Id": "Part2",
			"Name": "髪"
		},
		{
			"Id": "Part4",
			"Name": "顔"
		},
		{
			"Id": "Part9",
			"Name": "右_腕下"
		},
		{
			"Id": "Part10",
			"Name": "セーラー"
		},
		{
			"Id": "Part11",
			"Name": "首/シャツ"
		},
		{
			"Id": "Part12",
			"Name": "スカート"
		},
		{
			"Id": "Part13",
			"Name": "左_腕"
		},
		{
			"Id": "Part14",
			"Name": "脚"
		},
		{
			"Id": "Part5",
			"Name": "右_目"
		},
		{
			"Id": "Part6",
			"Name": "左_目"
		},
		{
			"Id": "Part7",
			"Name": "口"
		}
	],
	"CombinedParameters": [
		[
			"ParamAngleX",
			"ParamAngleY"
		],
		[
			"ParamEyeBallX",
			"ParamEyeBallY"
		],
		[
			"ParamMouthForm",
			"ParamMouthOpenY"
		]
	]
}